tc_xml_python/__init__.py
tc_xml_python/cli.py
tc_xml_python/globals.py
tc_xml_python/models.py
tc_xml_python/exceptions/__init__.py
tc_xml_python/exceptions/parsing.py
tc_xml_python/parsing/__init__.py
tc_xml_python/parsing/parser.py
tc_xml_python-0.3.1.dist-info/DESCRIPTION.rst
tc_xml_python-0.3.1.dist-info/METADATA
tc_xml_python-0.3.1.dist-info/RECORD
tc_xml_python-0.3.1.dist-info/WHEEL
tc_xml_python-0.3.1.dist-info/entry_points.txt
tc_xml_python-0.3.1.dist-info/metadata.json
tc_xml_python-0.3.1.dist-info/top_level.txt
tests/__init__.py
tests/test_basic.py
tests/test_models.py
tests/test_parser.py
tests/resources/xml_1_test.xml
tests/resources/xml_2_test.xml
