Metadata-Version: 2.0
Name: tc-xml-python
Version: 0.3.1
Summary: Lightweight implementation of the Typecraft XML format in python.
Home-page: https://github.com/Typecraft/tc_xml_python
Author: Tormod Haugland
Author-email: tormod.haugland@gmail.com
License: MIT license
Keywords: tc_xml_python
Platform: UNKNOWN
Classifier: Development Status :: 3 - Alpha
Classifier: Intended Audience :: Developers
Classifier: License :: OSI Approved :: MIT License
Classifier: Natural Language :: English
Classifier: Programming Language :: Python :: 2
Classifier: Programming Language :: Python :: 2.6
Classifier: Programming Language :: Python :: 2.7
Classifier: Programming Language :: Python :: 3
Classifier: Programming Language :: Python :: 3.3
Classifier: Programming Language :: Python :: 3.4
Classifier: Programming Language :: Python :: 3.5
Requires-Dist: Click (>=6.0)
